README.md
setup.py
shellson/__init__.py
shellson/__main__.py
shellson.egg-info/PKG-INFO
shellson.egg-info/SOURCES.txt
shellson.egg-info/dependency_links.txt
shellson.egg-info/entry_points.txt
shellson.egg-info/top_level.txt
test/test_main.py