Metadata-Version: 1.0
Name: shellson
Version: 0.2.0
Summary: JSON command line parser
Home-page: https://github.com/logileifs/shellson
Author: Logi og Fjalar
Author-email: logileifs@gmail.com
License: UNKNOWN
Platform: UNKNOWN
